biocentral_api/__init__.py
biocentral_api/api.py
biocentral_api/_generated/__init__.py
biocentral_api/_generated/api_client.py
biocentral_api/_generated/api_response.py
biocentral_api/_generated/configuration.py
biocentral_api/_generated/exceptions.py
biocentral_api/_generated/py.typed
biocentral_api/_generated/rest.py
biocentral_api/_generated/api/__init__.py
biocentral_api/_generated/api/bayesian_optimization_api.py
biocentral_api/_generated/api/biocentral_api.py
biocentral_api/_generated/api/custom_models_api.py
biocentral_api/_generated/api/default_api.py
biocentral_api/_generated/api/embeddings_api.py
biocentral_api/_generated/api/plm_eval_api.py
biocentral_api/_generated/api/ppi_api.py
biocentral_api/_generated/api/prediction_api.py
biocentral_api/_generated/api/prediction_models_api.py
biocentral_api/_generated/api/projections_api.py
biocentral_api/_generated/api/proteins_api.py
biocentral_api/_generated/models/__init__.py
biocentral_api/_generated/models/add_embeddings_request.py
biocentral_api/_generated/models/add_embeddings_response.py
biocentral_api/_generated/models/auto_detect_format_request.py
biocentral_api/_generated/models/auto_eval_progress.py
biocentral_api/_generated/models/bayesian_optimization_request.py
biocentral_api/_generated/models/biocentral_server_custom_models_endpoint_models_error_response.py
biocentral_api/_generated/models/biocentral_server_prediction_models_endpoint_models_error_response.py
biocentral_api/_generated/models/biocentral_server_server_management_shared_endpoint_models_error_models_error_response.py
biocentral_api/_generated/models/biotrainer_sequence_record.py
biocentral_api/_generated/models/config_options_response.py
biocentral_api/_generated/models/config_verification_request.py
biocentral_api/_generated/models/config_verification_response.py
biocentral_api/_generated/models/continuous_optimization_config.py
biocentral_api/_generated/models/detected_format_response.py
biocentral_api-1.0.0.dist-info/licenses/LICENSE
biocentral_api-1.0.0.dist-info/METADATA
biocentral_api-1.0.0.dist-info/WHEEL
biocentral_api-1.0.0.dist-info/top_level.txt
biocentral_api-1.0.0.dist-info/RECORD
