Metadata-Version: 2.4
Name: biocentral_api
Version: 1.0.0
Summary: Programmatic access to the biocentral ecosystem.
Author-email: Sebastian Franz <sebastian.franz@tum.de>
Project-URL: Repository, https://github.com/biocentral/biocentral_api/
Keywords: OpenAPI,OpenAPI-Generator,Biocentral Server,Biocentral
Requires-Python: >=3.9
License-File: LICENSE
Requires-Dist: urllib3<3.0.0,>=2.1.0
Requires-Dist: python-dateutil>=2.8.2
Requires-Dist: pydantic>=2
Requires-Dist: typing-extensions>=4.7.1
Requires-Dist: h5py>=3.14.0
Requires-Dist: tqdm>=4.67.1
Dynamic: license-file
